mcp_sentry_custom/__init__.py
mcp_sentry_custom/main.py
mcp_sentry_custom/server.py
mcp_sentry_custom-0.6.4.dist-info/METADATA
mcp_sentry_custom-0.6.4.dist-info/WHEEL
mcp_sentry_custom-0.6.4.dist-info/entry_points.txt
mcp_sentry_custom-0.6.4.dist-info/RECORD
