Metadata-Version: 2.4
Name: mcp-sentry-custom
Version: 0.6.4
Summary: MCP server for retrieving issues from sentry.io or self-hosted Sentry instances
Project-URL: Homepage, https://github.com/javaDer/mcp-sentry-custom
Project-URL: Bug Tracker, https://github.com/javaDer/mcp-sentry-custom/issues
Requires-Python: >=3.10
Requires-Dist: mcp>=1.0.0
